mvent/__init__.py
mvent-1.0.3.dist-info/LICENSE
mvent-1.0.3.dist-info/METADATA
mvent-1.0.3.dist-info/WHEEL
mvent-1.0.3.dist-info/top_level.txt
mvent-1.0.3.dist-info/RECORD
