Metadata-Version: 2.1
Name: mvent
Version: 1.0.3
Summary: A shared memory event system for Python
Home-page: https://github.com/cognition-brahmai/mvent
Author: BRAHMAI
Author-email: open-source@brahmai.in
Classifier: Programming Language :: Python :: 3
Classifier: License :: OSI Approved :: MIT License
Classifier: Operating System :: OS Independent
Requires-Python: >=3.7
License-File: LICENSE
